{
    "starterProjects.starterProjects": "Εισαγωγικά Έργα",
    "starterProjects.thinkBigStartSmallTitle": "Think Big…But Start Small!",
    "starterProjects.thinkBigStartSmallBody": "Every Scratch project starts with a Scratch Cat. Try making it say hello, spinning it around, or changing its color. As you learn more, you can create anything you can imagine: stories, games, animations, and beyond!",
    "starterProjects.howToUseScratchTitle": "How to Use Starter Projects",
    "starterProjects.howToUseScratchBody": "Starter projects include some simple code you can remix to make your own creations, so you don’t have to start from scratch! Find notes inside the code to guide you. Click “Remix,” then “See Inside” to get started.",
    "starterProjects.animation": "Κινούμενα σχέδια",
    "starterProjects.games": "Παιχνίδια",
    "starterProjects.interactiveArt": "Διαδραστική Τέχνη",
    "starterProjects.music": "Μουσική",
    "starterProjects.stories": "Ιστορίες",
    "starterProjects.mathScience": "Math and Science",
    "starterProjects.extensions": "Επεκτάσεις",
    "starterProjects.communityKindness": "Community and Kindness",
    "starterProjects.surpriseMe": "Surprise me",
    "starterProjects.gettingStarted": "Ξεκινώντας",
    "starterProjects.newToScratch": "Νέοι στο Scratch; Δοκιμάστε το εκπαιδευτικό υλικό Ξεκινώντας.",
    "starterProjects.gettingStartedImageDescription": "An illustrated boy plants his flag on top of a freshly painted mountaintop.",
    "starterProjects.tryIt": "Δοκιμάστε το!"
}