{
	"sec.title": "«Սքրեչ» կրթական համագործակցութիւն (ՍԿՀ)",
	"sec.intro": "Մասնակից ընկերութիւններ",
	"sec.applyNow": "Դիմել հիմա",
	"sec.applyBanner": "Դիմումները ներկայիս փակուած են։ 2021 թուականի ՍԿՀ‑ին դիմելու վերջնաժամկէտը Մարտ 1‑ն էր։",
	"sec.projectsTitle": "Մասնակից ընկերութիւններ",
	"sec.yearRange": "2021–2022",
	"sec.org1": "{org1Listing} — AK, ԱՄՆ",
	"sec.org2": "{org2Listing} — AR, ԱՄՆ",
	"sec.org3": "{org3Listing} — UT, ԱՄՆ",
	"sec.org4": "{org4Listing} — TX, ԱՄՆ",
	"sec.org5": "{org5Listing} — MS, ԱՄՆ",
	"sec.org6": "{org6Listing} — Սանթա Պարպարա, Պրազիլ",
	"sec.org7": "{org7Listing} — Սիտնի, Աւստրալիա",
	"sec.org8": "{org8Listing} — Մեմֆիս, Թենեսի, ԱՄՆ",
	"sec.org9": "{org9Listing} — Նիւ Եորք Սիթի, Նիւ Եորք, ԱՄՆ",
	"sec.org10": "{org10Listing} — Ճոս, Նիկերիա",
	"sec.org11": "{org11Listing} — Պալթիմոր, Մերիլենտ, ԱՄՆ",
	"sec.org12": "{org12Listing} — Յոհաննէսպուրկ, Հարաւային Ափրիկէ",
	"sec.org13": "{org13Listing} — Հայուըրտ, Քալիֆորնիա, ԱՄՆ",
	"sec.org14": "{org14Listing} — Համպըլ, Թեքսաս, ԱՄՆ",
	"sec.org15": "{org15Listing} — Կիլֆորտ, Միացեալ Թագաւորութիւն",
	"sec.org16": "{org16Listing} — Մեխիքօ, Մեքսիքա",
	"sec.org17": "{org17Listing} — Մոնրէալ, Քանատա",
	"sec.org18": "{org18Listing} — Քլարք Քաունթի դպրոցական շրջանը, Նեւատա, ԱՄՆ",
	"sec.org19": "{org19Listing} — Օթելլօ դպրոցական շրջանը, Ուաշինկթըն, ԱՄՆ",
	"sec.org20": "{org20Listing} — Ուկանտա",
	"sec.org21": "{org21Listing} — Նիւ Եորք Սիթի, Նիւ Եորք, ԱՄՆ",
	"sec.org22": "{org22Listing} — ԱՄՆ",
	"sec.org23": "{org23Listing} - FL, USA",
	"sec.org24": "{org24Listing} - NYC, NY, USA",
	"sec.org25": "{org25Listing} - NYC, NY, USA",
	"sec.org26": "{org26Listing}- Նիճերիա",
	"sec.org27": "{org27Listing}- Princeton, NJ, USA",
	"sec.org28": "{org28Listing}- Պանկալոր, Հնդկաստան",
	"sec.org29": "{org29Listing}- Յոհաննէսպուրկ, Հարաւ Ափրիկէ",
	"sec.org30": "{org30Listing} — Պարսելոնա, Սպանիա",
	"sec.org31": "{org31Listing} — Փնոմ Փէն, Քամպոտիա",
	"sec.org32": "{org32Listing} — Նայրոպի, Քենիա",
	"sec.org33": "{org33Listing} — Նայրոպի, Քենիա",
	"sec.org34": "{org34Listing} — Ճոհանըսպուրկ, Հարաւային Ափրիկէ",
	"sec.org35": "{org35Listing} — Շիքակօ հանրային դպրոցներ, Իլինոյ, ԱՄՆ",
	"sec.org36": "{org36Listing} — Լակոս, Նիկերիա",
	"sec.org37": "{org37Listing} — Խերոնա, Սպանիա",
	"sec.org38": "{org38Listing} — Հալիֆաքս, Նոր Շոթլանտիա",
	"sec.org39": "{org39Listing} — ԱՄՆ",
	"sec.org40": "{org40Listing} — Օվերի, Նիկերիա եւ Նայրոպի, Քենիա",
	"sec.partnerOrgsTitle": "Գործընկեր կազմակերպութիւններ",
	"sec.partnerOrg1": "{partnerOrg1Listing} — Քեմպրիճ, Միացեալ Թագաւորութիւն",
	"sec.partnerOrg2": "{partnerOrg2Listing} (նախկինում՝ {partnerOrg2FormerName}) — Սթենֆորտ, Քալիֆորնիա, ԱՄՆ",
	"sec.partnerOrg3": "{partnerOrg3Listing} — Իլինոյ, ԱՄՆ",
	"sec.partnerOrg4": "{partnerOrg4Listing} — Նիւ Օրլինզ, Լուիզիանա, ԱՄՆ",
	"sec.partnerOrg5": "{partnerOrg5Listing} — Պրազիլ",
	"sec.partnerOrg6": "{partnerOrg6Listing} — Սան Ֆրանսիսքօ, Քալիֆորնիա, ԱՄՆ",
}
