{
    "ethics.title": "Scratch財団 研究倫理規定",
    "ethics.intro1": "Scratch財団での私たちの使命は、若者にデジタルツールを提供し、想像し、創造し、共有し、学ぶための機会を提供することです。Scratchプラットフォームは、すべての子どもたちが創造的に考え、体系的に理由づけし、共同して活動するといった、今日の社会でみんなに必要なスキルを学ぶ、無料で、安全で、遊び心のある学習環境です。私たちは、この楽しい学習環境にて子どもたちを支援するため、教育関係者や家族らとともに、活動しています。",
    "ethics.intro2": "この倫理規定は、Scratch財団の従業員や関係者が、プラットフォーム、参加者の体験、教育や学習の成果、補助金を利用した活動などを改善するための研究や評価を行うときのガイドです。この財団での研究や評価はすべて以下の原則に従って行われます。",
    "ethics.principle1Title": "原則1: 参加者を守る。",
    "ethics.principle1": "{title}Scratch財団の職員や請負先は、参加者のプライバシーや機密性を尊重します。職員や請負先は、参加者や(未成年の場合)保護者の同意なしに、いかなる個人情報も開示しません。そして、私たちは、参加者に被害を与えることを避け、参加による利益を最大化することを目指します。研究活動への参加はすべて任意です: {researchEmailLink}に連絡すると、オプトアウトできます。",
    "ethics.principle2Title": "原則2: 透明性を持って率いる。",
    "ethics.principle2": "{title}データを収集する際、財団の職員と請負先は、目的、参加要件(時間と労力を含む)、参加に伴うリスク、データの保護・報告方法、参加者がオプトアウトするための方法、財団の関係連絡先を開示します。",
    "ethics.principle3Title": "原則3: データ利用の原則を順守する。",
    "ethics.principle3": "{title} 財団の職員と請負先は、データの安全性とScratch プライバシーポリシーやEU一般データ保護規則 (GDPR)などのデジタルプライバシーポリシーへの順守を保証します。"
}