{
    "tile.tutorial": "Micromundo",
    "tile.tryIt": "Experimente",
    "microworlds.title": "Micromundos Scratch",
    "microworlds.subTitle": "Pode iniciar-se no Scratch de muitas diferentes formas. Clique numa imagem para experimentar uma forma.",
    "microworlds.HipHopTitle": "Dança Hip Hop",
    "microworlds.FashionTitle": "Moda",
    "microworlds.HouseTitle": "Casa Interactiva",
    "microworlds.MakeMusicTitle": "Faça Música",
    "microworlds.SoccerTitle": "Futebol",
    "microworlds.JokeTitle": "Fazer uma Piada",
    "microworlds.ArtTitle": "Criar Arte"
}
