{
    "studio.tabNavProjects": "Projekty",
    "studio.tabNavCurators": "Správcovia",
    "studio.tabNavComments": "Comments",
    "studio.tabNavActivity": "Activity",
    "studio.title": "Title",
    "studio.description": "Popis",
    "studio.thumbnail": "Thumbnail",
    "studio.projectsHeader": "Projekty",
    "studio.addProjectsHeader": "Pridať projekty",
    "studio.addProject": "Pridať",
    "studio.creatorRole": "Studio Creator",
    "studio.managersHeader": "Managers",
    "studio.unfollowStudio": "Unfollow Studio",
    "studio.followStudio": "Follow Studio",
    "studio.curatorsHeader": "Správcovia",
    "studio.inviteCuratorsHeader": "Invite Curators",
    "studio.inviteCurator": "Pozvať",
    "studio.curatorAcceptInvite": "Accept Invite",
    "studio.commentsHeader": "Comments"
}