{
    "paint.paintEditor.hue": "Kleur",
    "paint.paintEditor.saturation": "Sêding",
    "paint.paintEditor.brightness": "Helderheid",
    "gui.comingSoon.message1": "Gjin need, wy wurkje deroan {emoji}",
    "gui.comingSoon.message2": "Meikoarten...",
    "gui.comingSoon.message3": "Wy wurkje deroan {emoji}",
    "paint.paintEditor.costume": "Kostúm",
    "paint.paintEditor.group": "Groep",
    "paint.paintEditor.ungroup": "Ut groep helje",
    "paint.paintEditor.undo": "Ungedien meitsje",
    "paint.paintEditor.redo": "Op 'e nij dwaan",
    "paint.paintEditor.forward": "Foarút",
    "paint.paintEditor.backward": "Efterút",
    "paint.paintEditor.front": "Foarkant",
    "paint.paintEditor.back": "Werom",
    "paint.paintEditor.more": "Mear",
    "paint.modeTools.brushSize": "Grutte",
    "paint.modeTools.eraserSize": "Gumgrutte",
    "paint.modeTools.copy": "Kopiearje",
    "paint.modeTools.paste": "Plakke",
    "paint.modeTools.delete": "Fuorthelje",
    "paint.modeTools.curved": "Bûgd",
    "paint.modeTools.pointed": "Oanwiisd",
    "paint.modeTools.thickness": "Dikte",
    "paint.modeTools.flipHorizontal": "Horizontaal omdraaie",
    "paint.modeTools.flipVertical": "Fertikaal omdraaie",
    "paint.modeTools.filled": "Folle",
    "paint.modeTools.outlined": "Bûtenste râne",
    "paint.paintEditor.bitmap": "Omsette nei Bitmap",
    "paint.paintEditor.vector": "Omsette nei Fektor",
    "paint.paintEditor.fill": "Folje",
    "paint.paintEditor.stroke": "Râne",
    "paint.brushMode.brush": "Kwast",
    "paint.eraserMode.eraser": "Gum",
    "paint.fillMode.fill": "Folje",
    "paint.lineMode.line": "Rigel",
    "paint.ovalMode.oval": "Sirkel",
    "paint.rectMode.rect": "Rjochthoek",
    "paint.reshapeMode.reshape": "Foarm feroarje",
    "paint.roundedRectMode.roundedRect": "Rjochthoek mei rûne hoeken",
    "paint.selectMode.select": "Selektearje",
    "paint.textMode.text": "Tekst",
    "paint.colorPicker.swap": "Ruilje"
}